{
    "e": {
        "difficile": {
            "Victoire": 2,
            "Defaite": 4,
            "Egalite": 0
        },
        "virtuoso": {
            "Victoire": 1,
            "Defaite": 29,
            "Egalite": 0
        },
        "facile": {
            "Victoire": 124,
            "Defaite": 10,
            "Egalite": 3
        },
        "moyen": {
            "Victoire": 1,
            "Defaite": 0,
            "Egalite": 0
        },
        "extreme": {
            "Victoire": 0,
            "Defaite": 7,
            "Egalite": 3
        }
    },
    "admin": {
        "facile": {
            "Victoire": 19,
            "Defaite": 0,
            "Egalite": 0
        }
    },
    "bite": {
        "facile": {
            "Victoire": 1,
            "Defaite": 0,
            "Egalite": 0
        }
    },
    "testerPRO": {
        "facile": {
            "Victoire": 1,
            "Defaite": 0,
            "Egalite": 0
        }
    },
    "pseudo": {
        "facile": {
            "Victoire": 1,
            "Defaite": 1,
            "Egalite": 0
        }
    },
    "thomas": {
        "virtuoso": {
            "Victoire": 0,
            "Defaite": 1,
            "Egalite": 0
        },
        "facile": {
            "Victoire": 8,
            "Defaite": 1,
            "Egalite": 0
        }
    }
}